setup.py
boilerpot/__init__.py
boilerpot/__main__.py
boilerpot/boilerpot.py
boilerpot/cleaners.py
boilerpot.egg-info/PKG-INFO
boilerpot.egg-info/SOURCES.txt
boilerpot.egg-info/dependency_links.txt
boilerpot.egg-info/top_level.txt
boilerpot.egg-info/zip-safe