Metadata-Version: 1.1
Name: boilerpot
Version: 0.92
Summary: HTML content extraction
Home-page: http://github.com/jackdied/boilerpot
Author: Jack Diederich
Author-email: jackdied@gmail.com
License: Apache License
Keywords: html,scraping,templating
Platform: UNKNOWN
Classifier: Intended Audience :: Developers
Classifier: Intended Audience :: System Administrators
Classifier: License :: OSI Approved :: Apache Software License
Classifier: Programming Language :: Python
Classifier: Development Status :: 4 - Beta
Classifier: Programming Language :: Python
Classifier: Programming Language :: Python :: 2.7
Classifier: Operating System :: OS Independent
Classifier: Topic :: Software Development :: Libraries
Classifier: Topic :: Software Development :: Libraries :: Python Modules
